test1288/__init__.py
test1288/live-scraping-firebase-adminsdk-gck9g-011e4f00e1.json
test1288/script_tracker.py
test1288-0.1.dist-info/METADATA
test1288-0.1.dist-info/WHEEL
test1288-0.1.dist-info/top_level.txt
test1288-0.1.dist-info/RECORD
